MANIFEST.in
README.md
setup.py
Kozinaki.egg-info/SOURCES.txt
kozinaki/__init__.py
kozinaki/driver.py
kozinaki/exceptions.py
kozinaki/network.py
kozinaki/utils.py
kozinaki.egg-info/PKG-INFO
kozinaki.egg-info/SOURCES.txt
kozinaki.egg-info/dependency_links.txt
kozinaki.egg-info/entry_points.txt
kozinaki.egg-info/requires.txt
kozinaki.egg-info/top_level.txt
kozinaki/manage/__init__.py
kozinaki/manage/__main__.py
kozinaki/manage/config.yaml
kozinaki/manage/manage.py
kozinaki/manage/providers.json
kozinaki/manage/utils.py
kozinaki/manage/templates/nova_base.conf
kozinaki/manage/templates/nova_systemd_service.conf
kozinaki/manage/templates/ovs.conf
kozinaki/manage/templates/ovs_systemd_service.conf
kozinaki/manage/templates/providers/aws.conf
kozinaki/manage/templates/providers/azure.conf
kozinaki/manage/templates/providers/gcp.conf
kozinaki/providers/__init__.py
kozinaki/providers/common.py
kozinaki/providers/aws/__init__.py
kozinaki/providers/aws/config.py
kozinaki/providers/aws/provider.py
kozinaki/providers/azure/__init__.py
kozinaki/providers/azure/provider.py
kozinaki/providers/gcp/__init__.py
kozinaki/providers/gcp/provider.py
kozinaki/providers/libcloud/__init__.py
kozinaki/providers/libcloud/config.py
kozinaki/providers/libcloud/provider.py