Metadata-Version: 1.0
Name: kozinaki
Version: 0.1.7
Summary: OpenStack multi-cloud driver for AWS, Azure
Home-page: https://github.com/compunova/kozinaki.git
Author: Compunova
Author-email: kozinaki@compu-nova.com
License: UNKNOWN
Platform: UNKNOWN
